AUTHORS
LICENSE
MANIFEST.in
README.rst
setup.py
chart/__init__.py
chart/admin.py
chart/generator.py
chart/models.py
chart/tests.py
chart/urls.py
chart/views.py
chart/management/__init__.py
chart/management/commands/__init__.py
chart/management/commands/chartupdate.py
chart/templates/chart/chartentry_list.html
chart/templates/chart/inclusion_tags/chartentry_list_wide.html
chart/templates/chart/inclusion_tags/chartentry_listing.html
chart/templatetags/__init__.py
chart/templatetags/chart_inclusion_tags.py
panya_chart.egg-info/PKG-INFO
panya_chart.egg-info/SOURCES.txt
panya_chart.egg-info/dependency_links.txt
panya_chart.egg-info/not-zip-safe
panya_chart.egg-info/requires.txt
panya_chart.egg-info/top_level.txt